agentic_resume_builder/__init__.py
agentic_resume_builder/agent_tools.py
agentic_resume_builder/api.py
agentic_resume_builder/cli.py
agentic_resume_builder/config.py
agentic_resume_builder/document_converter.py
agentic_resume_builder/exceptions.py
agentic_resume_builder/markdown_processor.py
agentic_resume_builder/models.py
agentic_resume_builder/ollama_client.py
agentic_resume_builder/pdf_generator.py
agentic_resume_builder/resume_agent.py
agentic_resume_builder/resume_manager.py
agentic_resume_builder/session_manager.py
agentic_resume_builder/templates.py
agentic_resume_builder-0.1.0.dist-info/METADATA
agentic_resume_builder-0.1.0.dist-info/WHEEL
agentic_resume_builder-0.1.0.dist-info/entry_points.txt
agentic_resume_builder-0.1.0.dist-info/top_level.txt
agentic_resume_builder-0.1.0.dist-info/RECORD
